tiktok_session_lite_sdk/__init__.py
tiktok_session_lite_sdk-2.8.6.dist-info/METADATA
tiktok_session_lite_sdk-2.8.6.dist-info/WHEEL
tiktok_session_lite_sdk-2.8.6.dist-info/top_level.txt
tiktok_session_lite_sdk-2.8.6.dist-info/RECORD
