Metadata-Version: 2.1
Name: tiktok-session-lite-sdk
Version: 2.8.6
Summary: Library for handling session metrics on TT
Home-page: UNKNOWN
Author: chickenfox23
Author-email: chickenfox23@byt.com
License: UNKNOWN
Platform: UNKNOWN
Requires-Dist: requests
